{
    "id": 383,
    "date": "2021/01/08",
    "sources": [
        "https://www.washingtonpost.com/technology/2021/01/08/twitter-trump-dorsey/"
    ],
    "actions": [
        "open letter"
    ],
    "struggles": [
        "ethics"
    ],
    "employment_types": [
        "white collar workers"
    ],
    "description": "Following the pro-Trump storming of the Capitol on January 6, roughly 350 Twitter employees signed an internal letter addressed to CEO Jack Dorsey and top executives questioning Twitter's policies and role in facilitating the attack. The employees requested an investigation into corporation actions over the last several years and asked for greater transparency to the company\u2019s decision-making process regarding Donald Trumps' Twitter account on the day of the attack.",
    "online": true,
    "locations": [
        "usa"
    ],
    "companies": [
        "twitter"
    ],
    "workers": 350,
    "tags": [
        "trump",
        "politics"
    ],
    "author": [
        "CM"
    ],
    "latlngs": [
        [
            37.7762709,
            -122.41630688295965
        ]
    ],
    "addresses": [
        "Twitter, 875, Stevenson Street, Market Square, San Francisco, San Francisco City and County, California, 94102, United States"
    ]
}