{
    "id": 476,
    "date": "2021/10/12",
    "sources": [
        "https://www.theguardian.com/commentisfree/2021/oct/12/google-amazon-workers-condemn-project-nimbus-israeli-military-contract"
    ],
    "actions": [
        "open letter"
    ],
    "struggles": [
        "ethics"
    ],
    "employment_types": [
        "white collar workers",
        "contract workers",
        "inhouse workers"
    ],
    "description": "Google and Amazon workers condemn Amazon and Google\u2019s supplying to the Israeli military and government technology to harm Palestinians through Project Nimbus. They write that Project Nimbus would provide cloud services, including surveillance and data collection on Palestinians, that would support systematic discrimination and displacement. Workers released an internal letter, with 90+ Google workers and 300+ Amazon workers anonymously signing it.",
    "online": true,
    "locations": [
        "worldwide"
    ],
    "companies": [
        "google",
        "amazon"
    ],
    "workers": 391,
    "tags": [
        "international solidarity",
        "politics",
        "surveillance",
        "military_contracts",
        "industry solidarity",
        "ice"
    ],
    "author": [
        "wynniechan"
    ],
    "latlngs": null,
    "addresses": null
}